valori/__init__.py
valori/base.py
valori/client.py
valori/configs.py
valori/exceptions.py
valori/factory.py
valori/py.typed
valori/indices/__init__.py
valori/indices/annoy.py
valori/indices/base.py
valori/indices/flat.py
valori/indices/hnsw.py
valori/indices/ivf.py
valori/indices/lsh.py
valori/parsers/__init__.py
valori/parsers/base.py
valori/parsers/docling_parser.py
valori/parsers/llama_parser.py
valori/parsers/office_parser.py
valori/parsers/pdf_parser.py
valori/parsers/registry.py
valori/parsers/text_parser.py
valori/persistence/__init__.py
valori/persistence/base.py
valori/persistence/incremental.py
valori/persistence/tensor.py
valori/processors/__init__.py
valori/processors/base.py
valori/processors/chunking.py
valori/processors/cleaning.py
valori/processors/embedding.py
valori/processors/pipeline.py
valori/quantization/__init__.py
valori/quantization/base.py
valori/quantization/product.py
valori/quantization/saq.py
valori/quantization/scalar.py
valori/storage/__init__.py
valori/storage/base.py
valori/storage/disk.py
valori/storage/hybrid.py
valori/storage/memory.py
valori/utils/__init__.py
valori/utils/batch_manager.py
valori/utils/debugging.py
valori/utils/helpers.py
valori/utils/logging.py
valori/utils/similarity.py
valori/utils/validation.py
valori-0.1.5.dist-info/licenses/LICENSE
valori-0.1.5.dist-info/METADATA
valori-0.1.5.dist-info/WHEEL
valori-0.1.5.dist-info/entry_points.txt
valori-0.1.5.dist-info/top_level.txt
valori-0.1.5.dist-info/RECORD
