Metadata-Version: 2.4
Name: valori
Version: 0.1.5
Summary: A high-performance vector database library for Python
Home-page: https://github.com/varshith-Git/valori
Author: Varshith
Author-email: Varshith <varshith.gudur17@gmail.com>
Maintainer-email: Varshith <varshith.gudur17@gmail.com>
License: MIT
Project-URL: Homepage, https://github.com/varshith-Git/valori
Project-URL: Documentation, https://github.com/varshith-Git/valori
Project-URL: Repository, https://github.com/varshith-Git/valori.git
Project-URL: Bug Tracker, https://github.com/varshith-Git/valori/issues
Project-URL: Source Code, https://github.com/varshith-Git/valori
Keywords: vector,database,similarity,search,machine-learning,embeddings
Classifier: Development Status :: 4 - Beta
Classifier: Intended Audience :: Developers
Classifier: License :: OSI Approved :: MIT License
Classifier: Operating System :: OS Independent
Classifier: Programming Language :: Python :: 3
Classifier: Programming Language :: Python :: 3.8
Classifier: Programming Language :: Python :: 3.9
Classifier: Programming Language :: Python :: 3.10
Classifier: Programming Language :: Python :: 3.11
Classifier: Topic :: Scientific/Engineering :: Artificial Intelligence
Classifier: Topic :: Database
Classifier: Topic :: Software Development :: Libraries :: Python Modules
Requires-Python: >=3.8
License-File: LICENSE
Requires-Dist: numpy>=1.21.0
Requires-Dist: scikit-learn>=1.0.0
Requires-Dist: scipy>=1.7.0
Requires-Dist: psutil>=5.8.0
Requires-Dist: PyYAML>=6.0
Requires-Dist: chardet>=5.0.0
Provides-Extra: dev
Requires-Dist: pytest>=7.0.0; extra == "dev"
Requires-Dist: pytest-cov>=4.0.0; extra == "dev"
Requires-Dist: pytest-xdist>=3.0.0; extra == "dev"
Requires-Dist: black>=23.0.0; extra == "dev"
Requires-Dist: isort>=5.0.0; extra == "dev"
Requires-Dist: flake8>=6.0.0; extra == "dev"
Requires-Dist: mypy>=1.0.0; extra == "dev"
Requires-Dist: pre-commit>=3.0.0; extra == "dev"
Requires-Dist: safety>=2.0.0; extra == "dev"
Requires-Dist: bandit>=1.7.0; extra == "dev"
Requires-Dist: annoy==1.17.0; extra == "dev"
Provides-Extra: docs
Requires-Dist: sphinx>=7.0.0; extra == "docs"
Requires-Dist: sphinx-rtd-theme>=1.0.0; extra == "docs"
Provides-Extra: benchmark
Requires-Dist: matplotlib>=3.7.0; extra == "benchmark"
Requires-Dist: seaborn>=0.12.0; extra == "benchmark"
Requires-Dist: pandas>=2.0.0; extra == "benchmark"
Provides-Extra: parsing
Requires-Dist: PyPDF2>=3.0.0; extra == "parsing"
Requires-Dist: python-docx>=0.8.11; extra == "parsing"
Requires-Dist: openpyxl>=3.1.0; extra == "parsing"
Requires-Dist: python-pptx>=0.6.21; extra == "parsing"
Requires-Dist: nltk>=3.8.0; extra == "parsing"
Requires-Dist: beautifulsoup4>=4.12.0; extra == "parsing"
Requires-Dist: sentence-transformers>=2.2.0; extra == "parsing"
Dynamic: author
Dynamic: home-page
Dynamic: license-file
Dynamic: requires-python
